lropt/__init__.py
lropt/_version.py
lropt/extra.py
lropt/robust_problem.py
lropt/settings.py
lropt/uncertain.py
lropt/utils.py
lropt/remove_uncertain/__init__.py
lropt/remove_uncertain/remove_uncertain.py
lropt/remove_uncertain/atom_canonicalizers/__init__.py
lropt/remove_uncertain/atom_canonicalizers/add_canon.py
lropt/remove_uncertain/atom_canonicalizers/mul_canon.py
lropt/remove_uncertain/atom_canonicalizers/mulexpression_canon.py
lropt/remove_uncertain/atom_canonicalizers/quad_canon.py
lropt/uncertain_atoms/__init__.py
lropt/uncertain_atoms/max_affine.py
lropt/uncertain_atoms/quad_form.py
lropt/uncertain_canon/__init__.py
lropt/uncertain_canon/separate_uncertain_params.py
lropt/uncertain_canon/uncertain_canonicalization.py
lropt/uncertain_canon/uncertain_chain.py
lropt/uncertain_canon/remove_constant/__init__.py
lropt/uncertain_canon/remove_constant/mulexpression_rm.py
lropt/uncertain_canon/remove_constant/multiply_rm.py
lropt/uncertain_canon/separate_uncertainty/__init__.py
lropt/uncertain_canon/separate_uncertainty/addexpression_sep.py
lropt/uncertain_canon/separate_uncertainty/inequality_sep.py
lropt/uncertain_canon/separate_uncertainty/maximum_sep.py
lropt/uncertain_canon/separate_uncertainty/mulexpression_sep.py
lropt/uncertain_canon/separate_uncertainty/multiply_sep.py
lropt/uncertain_canon/separate_uncertainty/negexpression_sep.py
lropt/uncertain_canon/separate_uncertainty/quadform_sep.py
lropt/uncertainty_sets/__init__.py
lropt/uncertainty_sets/box.py
lropt/uncertainty_sets/budget.py
lropt/uncertainty_sets/ellipsoidal.py
lropt/uncertainty_sets/mro.py
lropt/uncertainty_sets/norm.py
lropt/uncertainty_sets/polyhedral.py
lropt/uncertainty_sets/uncertainty_set.py
lropt-0.0.1.dev0.dist-info/LICENSE
lropt-0.0.1.dev0.dist-info/METADATA
lropt-0.0.1.dev0.dist-info/WHEEL
lropt-0.0.1.dev0.dist-info/top_level.txt
lropt-0.0.1.dev0.dist-info/RECORD
